<?xml version="1.0" encoding="utf-8"?>
<odoo>
    <data noupdate="0">
        <!-- Demo Subscription Products -->
        
        <!-- Professional Membership Subscription -->
        <record id="subscription_professional_membership" model="ams.subscription.product">
            <field name="name">Professional Membership</field>
            <field name="code">SUB_PROF_MEM</field>
            <field name="product_id" ref="ams_products_base.sample_product_tshirt"/>
            <field name="subscription_scope">individual</field>
            <field name="product_type">membership</field>
            <field name="default_duration">12</field>
            <field name="duration_unit">months</field>
            <field name="default_price">250.00</field>
            <field name="currency_id" ref="base.USD"/>
            <field name="is_renewable">True</field>
            <field name="renewal_window_days">90</field>
            <field name="auto_renewal_enabled">True</field>
            <field name="member_only">False</field>
            <field name="requires_approval">False</field>
            <field name="description"><![CDATA[
                <p>Professional membership includes:</p>
                <ul>
                    <li>Access to all professional development resources</li>
                    <li>Quarterly industry reports</li>
                    <li>Networking events and conferences</li>
                    <li>Professional certification opportunities</li>
                    <li>Online learning platform access</li>
                </ul>
            ]]></field>
            <field name="active">True</field>
        </record>

        <!-- Student Membership Subscription -->
        <record id="subscription_student_membership" model="ams.subscription.product">
            <field name="name">Student Membership</field>
            <field name="code">SUB_STUDENT_MEM</field>
            <field name="product_id" ref="ams_products_base.sample_product_mug"/>
            <field name="subscription_scope">individual</field>
            <field name="product_type">membership</field>
            <field name="default_duration">12</field>
            <field name="duration_unit">months</field>
            <field name="default_price">75.00</field>
            <field name="currency_id" ref="base.USD"/>
            <field name="is_renewable">True</field>
            <field name="renewal_window_days">90</field>
            <field name="auto_renewal_enabled">True</field>
            <field name="member_only">False</field>
            <field name="requires_approval">True</field>
            <field name="description"><![CDATA[
                <p>Student membership designed for current students and recent graduates:</p>
                <ul>
                    <li>Access to student resources and career services</li>
                    <li>Mentorship program participation</li>
                    <li>Student-focused events and workshops</li>
                    <li>Career placement assistance</li>
                    <li>Reduced-rate conference attendance</li>
                </ul>
            ]]></field>
            <field name="active">True</field>
        </record>

        <!-- Journal Subscription -->
        <record id="subscription_professional_journal" model="ams.subscription.product">
            <field name="name">Professional Journal</field>
            <field name="code">SUB_JOURNAL</field>
            <field name="product_id" ref="ams_products_base.sample_product_journal"/>
            <field name="subscription_scope">individual</field>
            <field name="product_type">publication</field>
            <field name="default_duration">12</field>
            <field name="duration_unit">months</field>
            <field name="default_price">120.00</field>
            <field name="currency_id" ref="base.USD"/>
            <field name="is_renewable">True</field>
            <field name="renewal_window_days">60</field>
            <field name="auto_renewal_enabled">True</field>
            <field name="member_only">False</field>
            <field name="requires_approval">False</field>
            <field name="description"><![CDATA[
                <p>Monthly professional journal subscription includes:</p>
                <ul>
                    <li>12 monthly issues delivered digitally</li>
                    <li>Archive access to past 5 years</li>
                    <li>Supplementary research reports</li>
                    <li>Early access to special issues</li>
                    <li>Optional print edition (additional fee)</li>
                </ul>
            ]]></field>
            <field name="active">True</field>
        </record>

        <!-- Demo Pricing Tiers - Only create if member types exist -->
        
        <!-- Professional Membership Pricing Tiers -->
        <record id="pricing_tier_prof_student" model="ams.subscription.pricing.tier">
            <field name="subscription_product_id" ref="subscription_professional_membership"/>
            <field name="member_type_id" ref="ams_member_data.member_type_student"/>
            <field name="price">125.00</field>
            <field name="currency_id" ref="base.USD"/>
            <field name="requires_verification">True</field>
            <field name="verification_criteria">Current student enrollment verification required</field>
            <field name="sequence">10</field>
            <field name="active">True</field>
        </record>

        <record id="pricing_tier_prof_senior" model="ams.subscription.pricing.tier">
            <field name="subscription_product_id" ref="subscription_professional_membership"/>
            <field name="member_type_id" ref="ams_member_data.member_type_retired"/>
            <field name="price">175.00</field>
            <field name="currency_id" ref="base.USD"/>
            <field name="requires_verification">True</field>
            <field name="verification_criteria">Retirement status verification required</field>
            <field name="sequence">20</field>
            <field name="active">True</field>
        </record>

        <!-- Journal Subscription Pricing Tiers -->
        <record id="pricing_tier_journal_member" model="ams.subscription.pricing.tier">
            <field name="subscription_product_id" ref="subscription_professional_journal"/>
            <field name="member_type_id" ref="ams_member_data.member_type_individual"/>
            <field name="price">96.00</field>
            <field name="currency_id" ref="base.USD"/>
            <field name="requires_verification">False</field>
            <field name="description">Member discount - 20% off regular price</field>
            <field name="sequence">10</field>
            <field name="active">True</field>
        </record>

    </data>
</odoo>